{
    "projectName": "projet1.angular",
    "decription": "Fichier de configuration de Taf",
    "taf_base_url": "https:\/\/shadonet.alwaysdata.net\/memoireiot.taf\/",
    "les_modules": [
        {
            "module": "home",
            "les_tables": [
                {
                    "table": "node_red",
                    "description": [
                        "id_node_red",
                        "link",
                        "uploaded_at"
                    ],
                    "table_descriptions": {
                        "table_name": "node_red",
                        "cle_primaire": {
                            "Field": "id_node_red",
                            "Type": "int(11)",
                            "Null": "NO",
                            "Key": "PRI",
                            "Default": null,
                            "Extra": "auto_increment",
                            "explications": "cl\u00e9 primaire"
                        },
                        "les_based_table_name": [
                            "node_red"
                        ],
                        "les_referenced_table": [],
                        "les_colonnes": [
                            {
                                "Field": "id_node_red",
                                "Type": "int(11)",
                                "Null": "NO",
                                "Key": "PRI",
                                "Default": null,
                                "Extra": "auto_increment",
                                "explications": "cl\u00e9 primaire"
                            },
                            {
                                "Field": "link",
                                "Type": "varchar(255)",
                                "Null": "NO",
                                "Key": "",
                                "Default": null,
                                "Extra": "",
                                "explications": ""
                            },
                            {
                                "Field": "uploaded_at",
                                "Type": "timestamp",
                                "Null": "NO",
                                "Key": "",
                                "Default": "current_timestamp()",
                                "Extra": "",
                                "explications": ""
                            }
                        ]
                    },
                    "les_types": [
                        "add",
                        "edit",
                        "list",
                        "details"
                    ]
                }
            ]
        }
    ]
}